{
	"dependency_sets": {
		"ubuntu24_04_integration_testing": {
			"sets": {
				"amd64": {
					"/noble-updates/binutils:amd64": "2.42-4ubuntu2.10",
					"/noble-updates/coreutils:amd64": "9.4-3ubuntu6.2",
					"/noble-updates/libatomic1:amd64": "14.2.0-4ubuntu2~24.04.1",
					"/noble-updates/libstdc++6:amd64": "14.2.0-4ubuntu2~24.04.1",
					"/noble/bash:amd64": "5.2.21-2ubuntu4"
				},
				"arm64": {
					"/noble-updates/binutils:arm64": "2.42-4ubuntu2.10",
					"/noble-updates/coreutils:arm64": "9.4-3ubuntu6.2",
					"/noble-updates/libatomic1:arm64": "14.2.0-4ubuntu2~24.04.1",
					"/noble-updates/libstdc++6:arm64": "14.2.0-4ubuntu2~24.04.1",
					"/noble/bash:arm64": "5.2.21-2ubuntu4"
				}
			}
		},
		"ubuntu24_04_sysroot": {
			"sets": {
				"amd64": {
					"/noble-updates/libatomic1:amd64": "14.2.0-4ubuntu2~24.04.1",
					"/noble-updates/libc6-dev:amd64": "2.39-0ubuntu8.7",
					"/noble-updates/libc6:amd64": "2.39-0ubuntu8.7",
					"/noble-updates/libgcc-s1:amd64": "14.2.0-4ubuntu2~24.04.1",
					"/noble-updates/libstdc++-13-dev:amd64": "13.3.0-6ubuntu2~24.04.1",
					"/noble-updates/libstdc++6:amd64": "14.2.0-4ubuntu2~24.04.1",
					"/noble-updates/linux-libc-dev:amd64": "6.8.0-106.106"
				},
				"arm64": {
					"/noble-updates/libatomic1:arm64": "14.2.0-4ubuntu2~24.04.1",
					"/noble-updates/libc6-dev:arm64": "2.39-0ubuntu8.7",
					"/noble-updates/libc6:arm64": "2.39-0ubuntu8.7",
					"/noble-updates/libgcc-s1:arm64": "14.2.0-4ubuntu2~24.04.1",
					"/noble-updates/libstdc++-13-dev:arm64": "13.3.0-6ubuntu2~24.04.1",
					"/noble-updates/libstdc++6:arm64": "14.2.0-4ubuntu2~24.04.1",
					"/noble-updates/linux-libc-dev:arm64": "6.8.0-106.106"
				}
			}
		}
	},
	"facts": {
		"noble-security/main/amd64/Packages": "sha256-OxZCuK+H23ehn64l48YaHq1U3tGmb6kx6elAcjBhzl4=",
		"noble-security/main/arm64/Packages": "sha256-HjlN3sGNO/w22bnPGd4Ev7KEbUl2FTvhDlWxsVqQldA=",
		"noble-updates/main/amd64/Packages": "sha256-2AE5TIdmI7YX74FdIKMjg7nV4+CC3JShKanAT9sshh0=",
		"noble-updates/main/arm64/Packages": "sha256-iflHMYRcSyIjxiN6xJzg5JEBbTwc8gwdyyleuif5Cn0=",
		"noble/main/amd64/Packages": "sha256-KmoZnhAxpcJ5yzRmRtWUmT81scA91KgqqgMjmA3ZJFE=",
		"noble/main/arm64/Packages": "sha256-ShkB5hJPsKER9d/8j1wUR09Eni7Ppx8urwspkX7bU/k="
	},
	"packages": {
		"/noble-updates/base-files:amd64=13ubuntu10.4": {
			"architecture": "amd64",
			"depends_on": [
				"/noble/libcrypt1:amd64=1:4.4.36-4build1",
				"/noble-updates/libc6:amd64=2.39-0ubuntu8.7",
				"/noble-updates/libgcc-s1:amd64=14.2.0-4ubuntu2~24.04.1",
				"/noble-updates/gcc-14-base:amd64=14.2.0-4ubuntu2~24.04.1",
				"/noble/mawk:amd64=1.3.4.20240123-1build1"
			],
			"filename": "pool/main/b/base-files/base-files_13ubuntu10.4_amd64.deb",
			"name": "base-files",
			"section": "admin",
			"sha256": "94daf9ede91f6263d676611623d4c9edab695c728a584ab2fb1d11cabb8479e8",
			"size": 73276,
			"suite": "noble-updates",
			"version": "13ubuntu10.4"
		},
		"/noble-updates/base-files:arm64=13ubuntu10.4": {
			"architecture": "arm64",
			"depends_on": [
				"/noble/libcrypt1:arm64=1:4.4.36-4build1",
				"/noble-updates/libc6:arm64=2.39-0ubuntu8.7",
				"/noble-updates/libgcc-s1:arm64=14.2.0-4ubuntu2~24.04.1",
				"/noble-updates/gcc-14-base:arm64=14.2.0-4ubuntu2~24.04.1",
				"/noble/mawk:arm64=1.3.4.20240123-1build1"
			],
			"filename": "pool/main/b/base-files/base-files_13ubuntu10.4_arm64.deb",
			"name": "base-files",
			"section": "admin",
			"sha256": "1b22f149ae67c1995615be284899e7b6bb1eed32884944905ab8414f44bbcf0a",
			"size": 73410,
			"suite": "noble-updates",
			"version": "13ubuntu10.4"
		},
		"/noble-updates/binutils-aarch64-linux-gnu:arm64=2.42-4ubuntu2.10": {
			"architecture": "arm64",
			"depends_on": [
				"/noble-updates/zlib1g:arm64=1:1.3.dfsg-3.1ubuntu2.1",
				"/noble-updates/libc6:arm64=2.39-0ubuntu8.7",
				"/noble-updates/libgcc-s1:arm64=14.2.0-4ubuntu2~24.04.1",
				"/noble-updates/gcc-14-base:arm64=14.2.0-4ubuntu2~24.04.1",
				"/noble-updates/libzstd1:arm64=1.5.5+dfsg2-2build1.1",
				"/noble-updates/libstdc++6:arm64=14.2.0-4ubuntu2~24.04.1",
				"/noble-updates/libsframe1:arm64=2.42-4ubuntu2.10",
				"/noble/libjansson4:arm64=2.14-2build2",
				"/noble-updates/libgprofng0:arm64=2.42-4ubuntu2.10",
				"/noble-updates/libbinutils:arm64=2.42-4ubuntu2.10",
				"/noble-updates/binutils-common:arm64=2.42-4ubuntu2.10",
				"/noble-updates/libctf0:arm64=2.42-4ubuntu2.10",
				"/noble-updates/libctf-nobfd0:arm64=2.42-4ubuntu2.10"
			],
			"filename": "pool/main/b/binutils/binutils-aarch64-linux-gnu_2.42-4ubuntu2.10_arm64.deb",
			"name": "binutils-aarch64-linux-gnu",
			"section": "devel",
			"sha256": "b5311d11d56f2daa82e952612b9578ef675af67714edb9aef7e3dc6cf2531575",
			"size": 3304470,
			"suite": "noble-updates",
			"version": "2.42-4ubuntu2.10"
		},
		"/noble-updates/binutils-common:amd64=2.42-4ubuntu2.10": {
			"architecture": "amd64",
			"depends_on": [],
			"filename": "pool/main/b/binutils/binutils-common_2.42-4ubuntu2.10_amd64.deb",
			"name": "binutils-common",
			"section": "devel",
			"sha256": "d136073f5e2153f3df11c1d08d66727b9466b28ff483f50085f14bbe3464b5ee",
			"size": 240286,
			"suite": "noble-updates",
			"version": "2.42-4ubuntu2.10"
		},
		"/noble-updates/binutils-common:arm64=2.42-4ubuntu2.10": {
			"architecture": "arm64",
			"depends_on": [],
			"filename": "pool/main/b/binutils/binutils-common_2.42-4ubuntu2.10_arm64.deb",
			"name": "binutils-common",
			"section": "devel",
			"sha256": "e2930005b9e4d599cfa8ebddd1d888cbcef7ebec38c8c7dfbc4babbdeaa52c3b",
			"size": 240286,
			"suite": "noble-updates",
			"version": "2.42-4ubuntu2.10"
		},
		"/noble-updates/binutils-x86-64-linux-gnu:amd64=2.42-4ubuntu2.10": {
			"architecture": "amd64",
			"depends_on": [
				"/noble-updates/zlib1g:amd64=1:1.3.dfsg-3.1ubuntu2.1",
				"/noble-updates/libc6:amd64=2.39-0ubuntu8.7",
				"/noble-updates/libgcc-s1:amd64=14.2.0-4ubuntu2~24.04.1",
				"/noble-updates/gcc-14-base:amd64=14.2.0-4ubuntu2~24.04.1",
				"/noble-updates/libzstd1:amd64=1.5.5+dfsg2-2build1.1",
				"/noble-updates/libstdc++6:amd64=14.2.0-4ubuntu2~24.04.1",
				"/noble-updates/libsframe1:amd64=2.42-4ubuntu2.10",
				"/noble/libjansson4:amd64=2.14-2build2",
				"/noble-updates/libgprofng0:amd64=2.42-4ubuntu2.10",
				"/noble-updates/libbinutils:amd64=2.42-4ubuntu2.10",
				"/noble-updates/binutils-common:amd64=2.42-4ubuntu2.10",
				"/noble-updates/libctf0:amd64=2.42-4ubuntu2.10",
				"/noble-updates/libctf-nobfd0:amd64=2.42-4ubuntu2.10"
			],
			"filename": "pool/main/b/binutils/binutils-x86-64-linux-gnu_2.42-4ubuntu2.10_amd64.deb",
			"name": "binutils-x86-64-linux-gnu",
			"section": "devel",
			"sha256": "1e510a15f30208d39edcd840e48f26a77bbca7c417805eeccb1e3f7de198ef29",
			"size": 2462744,
			"suite": "noble-updates",
			"version": "2.42-4ubuntu2.10"
		},
		"/noble-updates/binutils:amd64=2.42-4ubuntu2.10": {
			"architecture": "amd64",
			"depends_on": [
				"/noble-updates/binutils-x86-64-linux-gnu:amd64=2.42-4ubuntu2.10",
				"/noble-updates/zlib1g:amd64=1:1.3.dfsg-3.1ubuntu2.1",
				"/noble-updates/libc6:amd64=2.39-0ubuntu8.7",
				"/noble-updates/libgcc-s1:amd64=14.2.0-4ubuntu2~24.04.1",
				"/noble-updates/gcc-14-base:amd64=14.2.0-4ubuntu2~24.04.1",
				"/noble-updates/libzstd1:amd64=1.5.5+dfsg2-2build1.1",
				"/noble-updates/libstdc++6:amd64=14.2.0-4ubuntu2~24.04.1",
				"/noble-updates/libsframe1:amd64=2.42-4ubuntu2.10",
				"/noble/libjansson4:amd64=2.14-2build2",
				"/noble-updates/libgprofng0:amd64=2.42-4ubuntu2.10",
				"/noble-updates/libbinutils:amd64=2.42-4ubuntu2.10",
				"/noble-updates/binutils-common:amd64=2.42-4ubuntu2.10",
				"/noble-updates/libctf0:amd64=2.42-4ubuntu2.10",
				"/noble-updates/libctf-nobfd0:amd64=2.42-4ubuntu2.10"
			],
			"filename": "pool/main/b/binutils/binutils_2.42-4ubuntu2.10_amd64.deb",
			"name": "binutils",
			"section": "devel",
			"sha256": "b3b5a84181a38fd191820b2cdcc1a3eeb1cd6333ad472f2092f96e81047e9c74",
			"size": 18154,
			"suite": "noble-updates",
			"version": "2.42-4ubuntu2.10"
		},
		"/noble-updates/binutils:arm64=2.42-4ubuntu2.10": {
			"architecture": "arm64",
			"depends_on": [
				"/noble-updates/binutils-aarch64-linux-gnu:arm64=2.42-4ubuntu2.10",
				"/noble-updates/zlib1g:arm64=1:1.3.dfsg-3.1ubuntu2.1",
				"/noble-updates/libc6:arm64=2.39-0ubuntu8.7",
				"/noble-updates/libgcc-s1:arm64=14.2.0-4ubuntu2~24.04.1",
				"/noble-updates/gcc-14-base:arm64=14.2.0-4ubuntu2~24.04.1",
				"/noble-updates/libzstd1:arm64=1.5.5+dfsg2-2build1.1",
				"/noble-updates/libstdc++6:arm64=14.2.0-4ubuntu2~24.04.1",
				"/noble-updates/libsframe1:arm64=2.42-4ubuntu2.10",
				"/noble/libjansson4:arm64=2.14-2build2",
				"/noble-updates/libgprofng0:arm64=2.42-4ubuntu2.10",
				"/noble-updates/libbinutils:arm64=2.42-4ubuntu2.10",
				"/noble-updates/binutils-common:arm64=2.42-4ubuntu2.10",
				"/noble-updates/libctf0:arm64=2.42-4ubuntu2.10",
				"/noble-updates/libctf-nobfd0:arm64=2.42-4ubuntu2.10"
			],
			"filename": "pool/main/b/binutils/binutils_2.42-4ubuntu2.10_arm64.deb",
			"name": "binutils",
			"section": "devel",
			"sha256": "f3333e2ef1b857f35905194f42e9541ff6a42bef8fbba6d8bb56abff460d4fa2",
			"size": 18116,
			"suite": "noble-updates",
			"version": "2.42-4ubuntu2.10"
		},
		"/noble-updates/coreutils:amd64=9.4-3ubuntu6.2": {
			"architecture": "amd64",
			"depends_on": [
				"/noble-updates/libssl3t64:amd64=3.0.13-0ubuntu3.7",
				"/noble-updates/libc6:amd64=2.39-0ubuntu8.7",
				"/noble-updates/libgcc-s1:amd64=14.2.0-4ubuntu2~24.04.1",
				"/noble-updates/gcc-14-base:amd64=14.2.0-4ubuntu2~24.04.1",
				"/noble-updates/libselinux1:amd64=3.5-2ubuntu2.1",
				"/noble-updates/libpcre2-8-0:amd64=10.42-4ubuntu2.1",
				"/noble-updates/libgmp10:amd64=2:6.3.0+dfsg-2ubuntu6.1",
				"/noble-updates/libattr1:amd64=1:2.5.2-1build1.1",
				"/noble-updates/libacl1:amd64=2.3.2-1build1.1"
			],
			"filename": "pool/main/c/coreutils/coreutils_9.4-3ubuntu6.2_amd64.deb",
			"name": "coreutils",
			"section": "utils",
			"sha256": "d623abbb182acfead9d6352252e687674b6e5b3b79d42aa1324b08a3a6e1131b",
			"size": 1411666,
			"suite": "noble-updates",
			"version": "9.4-3ubuntu6.2"
		},
		"/noble-updates/coreutils:arm64=9.4-3ubuntu6.2": {
			"architecture": "arm64",
			"depends_on": [
				"/noble-updates/libssl3t64:arm64=3.0.13-0ubuntu3.7",
				"/noble-updates/libc6:arm64=2.39-0ubuntu8.7",
				"/noble-updates/libgcc-s1:arm64=14.2.0-4ubuntu2~24.04.1",
				"/noble-updates/gcc-14-base:arm64=14.2.0-4ubuntu2~24.04.1",
				"/noble-updates/libselinux1:arm64=3.5-2ubuntu2.1",
				"/noble-updates/libpcre2-8-0:arm64=10.42-4ubuntu2.1",
				"/noble-updates/libgmp10:arm64=2:6.3.0+dfsg-2ubuntu6.1",
				"/noble-updates/libattr1:arm64=1:2.5.2-1build1.1",
				"/noble-updates/libacl1:arm64=2.3.2-1build1.1"
			],
			"filename": "pool/main/c/coreutils/coreutils_9.4-3ubuntu6.2_arm64.deb",
			"name": "coreutils",
			"section": "utils",
			"sha256": "68f2a7cc1e164d669df3f8b5c1903947e1a74844d24843cf770bc63691753f16",
			"size": 1362312,
			"suite": "noble-updates",
			"version": "9.4-3ubuntu6.2"
		},
		"/noble-updates/gcc-13-base:amd64=13.3.0-6ubuntu2~24.04.1": {
			"architecture": "amd64",
			"depends_on": [],
			"filename": "pool/main/g/gcc-13/gcc-13-base_13.3.0-6ubuntu2~24.04.1_amd64.deb",
			"name": "gcc-13-base",
			"section": "libs",
			"sha256": "e859aca26585bb91113a451f1e66bc0e5283cb08797d679aacc1d936ae6dff8e",
			"size": 51616,
			"suite": "noble-updates",
			"version": "13.3.0-6ubuntu2~24.04.1"
		},
		"/noble-updates/gcc-13-base:arm64=13.3.0-6ubuntu2~24.04.1": {
			"architecture": "arm64",
			"depends_on": [],
			"filename": "pool/main/g/gcc-13/gcc-13-base_13.3.0-6ubuntu2~24.04.1_arm64.deb",
			"name": "gcc-13-base",
			"section": "libs",
			"sha256": "1c1ca489da0d48237036318189a9b6525abe7703b75495f257f68bccae8c45a7",
			"size": 51632,
			"suite": "noble-updates",
			"version": "13.3.0-6ubuntu2~24.04.1"
		},
		"/noble-updates/gcc-14-base:amd64=14.2.0-4ubuntu2~24.04.1": {
			"architecture": "amd64",
			"depends_on": [],
			"filename": "pool/main/g/gcc-14/gcc-14-base_14.2.0-4ubuntu2~24.04.1_amd64.deb",
			"name": "gcc-14-base",
			"section": "libs",
			"sha256": "b95c172411a7fdae70307cf33a9f5320ba5e056b556454543dd5b679d5ce1c4f",
			"size": 51014,
			"suite": "noble-updates",
			"version": "14.2.0-4ubuntu2~24.04.1"
		},
		"/noble-updates/gcc-14-base:arm64=14.2.0-4ubuntu2~24.04.1": {
			"architecture": "arm64",
			"depends_on": [],
			"filename": "pool/main/g/gcc-14/gcc-14-base_14.2.0-4ubuntu2~24.04.1_arm64.deb",
			"name": "gcc-14-base",
			"section": "libs",
			"sha256": "bddbe21061fdc73a23e7de79ece91693bf61aa22d634d1c69c5048385c114968",
			"size": 50984,
			"suite": "noble-updates",
			"version": "14.2.0-4ubuntu2~24.04.1"
		},
		"/noble-updates/libacl1:amd64=2.3.2-1build1.1": {
			"architecture": "amd64",
			"depends_on": [
				"/noble-updates/libc6:amd64=2.39-0ubuntu8.7",
				"/noble-updates/libgcc-s1:amd64=14.2.0-4ubuntu2~24.04.1",
				"/noble-updates/gcc-14-base:amd64=14.2.0-4ubuntu2~24.04.1"
			],
			"filename": "pool/main/a/acl/libacl1_2.3.2-1build1.1_amd64.deb",
			"name": "libacl1",
			"section": "libs",
			"sha256": "f2bfd3f8f00413d5f1f04fc723063803c56ac0f1e0efae3bc41f2d7276972ec3",
			"size": 16792,
			"suite": "noble-updates",
			"version": "2.3.2-1build1.1"
		},
		"/noble-updates/libacl1:arm64=2.3.2-1build1.1": {
			"architecture": "arm64",
			"depends_on": [
				"/noble-updates/libc6:arm64=2.39-0ubuntu8.7",
				"/noble-updates/libgcc-s1:arm64=14.2.0-4ubuntu2~24.04.1",
				"/noble-updates/gcc-14-base:arm64=14.2.0-4ubuntu2~24.04.1"
			],
			"filename": "pool/main/a/acl/libacl1_2.3.2-1build1.1_arm64.deb",
			"name": "libacl1",
			"section": "libs",
			"sha256": "ebc53ded654fcf4449df250cb563ff05f10d851e904e638f698dc7e921ffa47b",
			"size": 17050,
			"suite": "noble-updates",
			"version": "2.3.2-1build1.1"
		},
		"/noble-updates/libasan8:amd64=14.2.0-4ubuntu2~24.04.1": {
			"architecture": "amd64",
			"depends_on": [
				"/noble-updates/libgcc-s1:amd64=14.2.0-4ubuntu2~24.04.1",
				"/noble-updates/libc6:amd64=2.39-0ubuntu8.7",
				"/noble-updates/gcc-14-base:amd64=14.2.0-4ubuntu2~24.04.1"
			],
			"filename": "pool/main/g/gcc-14/libasan8_14.2.0-4ubuntu2~24.04.1_amd64.deb",
			"name": "libasan8",
			"section": "libs",
			"sha256": "8321aac6230fa1da320e76eb6288b7436164624aec449ed3933ea6c4cc86daac",
			"size": 3026656,
			"suite": "noble-updates",
			"version": "14.2.0-4ubuntu2~24.04.1"
		},
		"/noble-updates/libasan8:arm64=14.2.0-4ubuntu2~24.04.1": {
			"architecture": "arm64",
			"depends_on": [
				"/noble-updates/libgcc-s1:arm64=14.2.0-4ubuntu2~24.04.1",
				"/noble-updates/libc6:arm64=2.39-0ubuntu8.7",
				"/noble-updates/gcc-14-base:arm64=14.2.0-4ubuntu2~24.04.1"
			],
			"filename": "pool/main/g/gcc-14/libasan8_14.2.0-4ubuntu2~24.04.1_arm64.deb",
			"name": "libasan8",
			"section": "libs",
			"sha256": "0b7957bc5bbc5d30eabe8b71bab06e624ac530be7b1b1315d2bd54629cf2559f",
			"size": 2927874,
			"suite": "noble-updates",
			"version": "14.2.0-4ubuntu2~24.04.1"
		},
		"/noble-updates/libatomic1:amd64=14.2.0-4ubuntu2~24.04.1": {
			"architecture": "amd64",
			"depends_on": [
				"/noble-updates/libc6:amd64=2.39-0ubuntu8.7",
				"/noble-updates/libgcc-s1:amd64=14.2.0-4ubuntu2~24.04.1",
				"/noble-updates/gcc-14-base:amd64=14.2.0-4ubuntu2~24.04.1"
			],
			"filename": "pool/main/g/gcc-14/libatomic1_14.2.0-4ubuntu2~24.04.1_amd64.deb",
			"name": "libatomic1",
			"section": "libs",
			"sha256": "fe49cbbc7be753528380c724a8eef5f1e31dffa9221f692c5069048d81c7449d",
			"size": 10466,
			"suite": "noble-updates",
			"version": "14.2.0-4ubuntu2~24.04.1"
		},
		"/noble-updates/libatomic1:arm64=14.2.0-4ubuntu2~24.04.1": {
			"architecture": "arm64",
			"depends_on": [
				"/noble-updates/libc6:arm64=2.39-0ubuntu8.7",
				"/noble-updates/libgcc-s1:arm64=14.2.0-4ubuntu2~24.04.1",
				"/noble-updates/gcc-14-base:arm64=14.2.0-4ubuntu2~24.04.1"
			],
			"filename": "pool/main/g/gcc-14/libatomic1_14.2.0-4ubuntu2~24.04.1_arm64.deb",
			"name": "libatomic1",
			"section": "libs",
			"sha256": "fdeab74e7ad8572cf69c7024e8040c7ac851f6e667d35f0d429e7a0352840f73",
			"size": 11604,
			"suite": "noble-updates",
			"version": "14.2.0-4ubuntu2~24.04.1"
		},
		"/noble-updates/libattr1:amd64=1:2.5.2-1build1.1": {
			"architecture": "amd64",
			"depends_on": [
				"/noble-updates/libc6:amd64=2.39-0ubuntu8.7",
				"/noble-updates/libgcc-s1:amd64=14.2.0-4ubuntu2~24.04.1",
				"/noble-updates/gcc-14-base:amd64=14.2.0-4ubuntu2~24.04.1"
			],
			"filename": "pool/main/a/attr/libattr1_2.5.2-1build1.1_amd64.deb",
			"name": "libattr1",
			"section": "libs",
			"sha256": "d880fdb65dec669fcc4c5b34c5cbfee6c014ec4bdf6430ecdc7f10efffb28b2e",
			"size": 11354,
			"suite": "noble-updates",
			"version": "1:2.5.2-1build1.1"
		},
		"/noble-updates/libattr1:arm64=1:2.5.2-1build1.1": {
			"architecture": "arm64",
			"depends_on": [
				"/noble-updates/libc6:arm64=2.39-0ubuntu8.7",
				"/noble-updates/libgcc-s1:arm64=14.2.0-4ubuntu2~24.04.1",
				"/noble-updates/gcc-14-base:arm64=14.2.0-4ubuntu2~24.04.1"
			],
			"filename": "pool/main/a/attr/libattr1_2.5.2-1build1.1_arm64.deb",
			"name": "libattr1",
			"section": "libs",
			"sha256": "d441ec6f5df6ffa76d37fe5c7eecbd42ae1876121baf3e511de57afe79538f1d",
			"size": 11026,
			"suite": "noble-updates",
			"version": "1:2.5.2-1build1.1"
		},
		"/noble-updates/libbinutils:amd64=2.42-4ubuntu2.10": {
			"architecture": "amd64",
			"depends_on": [
				"/noble-updates/binutils-common:amd64=2.42-4ubuntu2.10",
				"/noble-updates/zlib1g:amd64=1:1.3.dfsg-3.1ubuntu2.1",
				"/noble-updates/libc6:amd64=2.39-0ubuntu8.7",
				"/noble-updates/libgcc-s1:amd64=14.2.0-4ubuntu2~24.04.1",
				"/noble-updates/gcc-14-base:amd64=14.2.0-4ubuntu2~24.04.1",
				"/noble-updates/libzstd1:amd64=1.5.5+dfsg2-2build1.1",
				"/noble-updates/libsframe1:amd64=2.42-4ubuntu2.10"
			],
			"filename": "pool/main/b/binutils/libbinutils_2.42-4ubuntu2.10_amd64.deb",
			"name": "libbinutils",
			"section": "devel",
			"sha256": "064dce00ce94e1fc2d33779cb0071088f4c8aac79e85345f2e78a020f7d14699",
			"size": 576834,
			"suite": "noble-updates",
			"version": "2.42-4ubuntu2.10"
		},
		"/noble-updates/libbinutils:arm64=2.42-4ubuntu2.10": {
			"architecture": "arm64",
			"depends_on": [
				"/noble-updates/binutils-common:arm64=2.42-4ubuntu2.10",
				"/noble-updates/zlib1g:arm64=1:1.3.dfsg-3.1ubuntu2.1",
				"/noble-updates/libc6:arm64=2.39-0ubuntu8.7",
				"/noble-updates/libgcc-s1:arm64=14.2.0-4ubuntu2~24.04.1",
				"/noble-updates/gcc-14-base:arm64=14.2.0-4ubuntu2~24.04.1",
				"/noble-updates/libzstd1:arm64=1.5.5+dfsg2-2build1.1",
				"/noble-updates/libsframe1:arm64=2.42-4ubuntu2.10"
			],
			"filename": "pool/main/b/binutils/libbinutils_2.42-4ubuntu2.10_arm64.deb",
			"name": "libbinutils",
			"section": "devel",
			"sha256": "c86634a7471aa27439b9bef7bd91ca8136f01f938c93bf6abe16a8fca758e849",
			"size": 766448,
			"suite": "noble-updates",
			"version": "2.42-4ubuntu2.10"
		},
		"/noble-updates/libc-dev-bin:amd64=2.39-0ubuntu8.7": {
			"architecture": "amd64",
			"depends_on": [
				"/noble-updates/libc6:amd64=2.39-0ubuntu8.7",
				"/noble-updates/libgcc-s1:amd64=14.2.0-4ubuntu2~24.04.1",
				"/noble-updates/gcc-14-base:amd64=14.2.0-4ubuntu2~24.04.1"
			],
			"filename": "pool/main/g/glibc/libc-dev-bin_2.39-0ubuntu8.7_amd64.deb",
			"name": "libc-dev-bin",
			"section": "libdevel",
			"sha256": "83291a1d9b26262ac8f44a3bb188ce2cb796a0543134aae00e19db066c84dfdd",
			"size": 20418,
			"suite": "noble-updates",
			"version": "2.39-0ubuntu8.7"
		},
		"/noble-updates/libc-dev-bin:arm64=2.39-0ubuntu8.7": {
			"architecture": "arm64",
			"depends_on": [
				"/noble-updates/libc6:arm64=2.39-0ubuntu8.7",
				"/noble-updates/libgcc-s1:arm64=14.2.0-4ubuntu2~24.04.1",
				"/noble-updates/gcc-14-base:arm64=14.2.0-4ubuntu2~24.04.1"
			],
			"filename": "pool/main/g/glibc/libc-dev-bin_2.39-0ubuntu8.7_arm64.deb",
			"name": "libc-dev-bin",
			"section": "libdevel",
			"sha256": "d76ef96feaf47f698661236af9f45d2eabd9805398f49b6c79f34145d636c337",
			"size": 19680,
			"suite": "noble-updates",
			"version": "2.39-0ubuntu8.7"
		},
		"/noble-updates/libc6-dev:amd64=2.39-0ubuntu8.7": {
			"architecture": "amd64",
			"depends_on": [
				"/noble/rpcsvc-proto:amd64=1.4.2-0ubuntu7",
				"/noble-updates/libc6:amd64=2.39-0ubuntu8.7",
				"/noble-updates/libgcc-s1:amd64=14.2.0-4ubuntu2~24.04.1",
				"/noble-updates/gcc-14-base:amd64=14.2.0-4ubuntu2~24.04.1",
				"/noble/libcrypt-dev:amd64=1:4.4.36-4build1",
				"/noble/libcrypt1:amd64=1:4.4.36-4build1",
				"/noble-updates/linux-libc-dev:amd64=6.8.0-106.106",
				"/noble-updates/libc-dev-bin:amd64=2.39-0ubuntu8.7"
			],
			"filename": "pool/main/g/glibc/libc6-dev_2.39-0ubuntu8.7_amd64.deb",
			"name": "libc6-dev",
			"section": "libdevel",
			"sha256": "bbf5a155039042634961a61276650631ee47b9e721f91f8dbb731b0bbe046df3",
			"size": 2124026,
			"suite": "noble-updates",
			"version": "2.39-0ubuntu8.7"
		},
		"/noble-updates/libc6-dev:arm64=2.39-0ubuntu8.7": {
			"architecture": "arm64",
			"depends_on": [
				"/noble/rpcsvc-proto:arm64=1.4.2-0ubuntu7",
				"/noble-updates/libc6:arm64=2.39-0ubuntu8.7",
				"/noble-updates/libgcc-s1:arm64=14.2.0-4ubuntu2~24.04.1",
				"/noble-updates/gcc-14-base:arm64=14.2.0-4ubuntu2~24.04.1",
				"/noble/libcrypt-dev:arm64=1:4.4.36-4build1",
				"/noble/libcrypt1:arm64=1:4.4.36-4build1",
				"/noble-updates/linux-libc-dev:arm64=6.8.0-106.106",
				"/noble-updates/libc-dev-bin:arm64=2.39-0ubuntu8.7"
			],
			"filename": "pool/main/g/glibc/libc6-dev_2.39-0ubuntu8.7_arm64.deb",
			"name": "libc6-dev",
			"section": "libdevel",
			"sha256": "d00158c84302fa21231a4cca4131de60134c2359ea8e5641b12e476bd5585aff",
			"size": 1596158,
			"suite": "noble-updates",
			"version": "2.39-0ubuntu8.7"
		},
		"/noble-updates/libc6:amd64=2.39-0ubuntu8.7": {
			"architecture": "amd64",
			"depends_on": [
				"/noble-updates/libgcc-s1:amd64=14.2.0-4ubuntu2~24.04.1",
				"/noble-updates/gcc-14-base:amd64=14.2.0-4ubuntu2~24.04.1"
			],
			"filename": "pool/main/g/glibc/libc6_2.39-0ubuntu8.7_amd64.deb",
			"name": "libc6",
			"section": "libs",
			"sha256": "955644e8bc2930a9bf8eea5e4c2237c8a118c1e2ac2845b993b6f7f35eefd293",
			"size": 3262920,
			"suite": "noble-updates",
			"version": "2.39-0ubuntu8.7"
		},
		"/noble-updates/libc6:arm64=2.39-0ubuntu8.7": {
			"architecture": "arm64",
			"depends_on": [
				"/noble-updates/libgcc-s1:arm64=14.2.0-4ubuntu2~24.04.1",
				"/noble-updates/gcc-14-base:arm64=14.2.0-4ubuntu2~24.04.1"
			],
			"filename": "pool/main/g/glibc/libc6_2.39-0ubuntu8.7_arm64.deb",
			"name": "libc6",
			"section": "libs",
			"sha256": "7d25b6ffc4df6deefd1a48efff5792d6a6bd89ac064a2a8b88e796d3d533e095",
			"size": 2776586,
			"suite": "noble-updates",
			"version": "2.39-0ubuntu8.7"
		},
		"/noble-updates/libctf-nobfd0:amd64=2.42-4ubuntu2.10": {
			"architecture": "amd64",
			"depends_on": [
				"/noble-updates/zlib1g:amd64=1:1.3.dfsg-3.1ubuntu2.1",
				"/noble-updates/libc6:amd64=2.39-0ubuntu8.7",
				"/noble-updates/libgcc-s1:amd64=14.2.0-4ubuntu2~24.04.1",
				"/noble-updates/gcc-14-base:amd64=14.2.0-4ubuntu2~24.04.1"
			],
			"filename": "pool/main/b/binutils/libctf-nobfd0_2.42-4ubuntu2.10_amd64.deb",
			"name": "libctf-nobfd0",
			"section": "devel",
			"sha256": "da352eb7fa6c4369d2a6c1e5e680f574eda2e38576563326b18d9e47e61c4078",
			"size": 98012,
			"suite": "noble-updates",
			"version": "2.42-4ubuntu2.10"
		},
		"/noble-updates/libctf-nobfd0:arm64=2.42-4ubuntu2.10": {
			"architecture": "arm64",
			"depends_on": [
				"/noble-updates/zlib1g:arm64=1:1.3.dfsg-3.1ubuntu2.1",
				"/noble-updates/libc6:arm64=2.39-0ubuntu8.7",
				"/noble-updates/libgcc-s1:arm64=14.2.0-4ubuntu2~24.04.1",
				"/noble-updates/gcc-14-base:arm64=14.2.0-4ubuntu2~24.04.1"
			],
			"filename": "pool/main/b/binutils/libctf-nobfd0_2.42-4ubuntu2.10_arm64.deb",
			"name": "libctf-nobfd0",
			"section": "devel",
			"sha256": "c80063890a430e42181e7ad3f0277bb563abc22d556fd5e65c798c4ee8318684",
			"size": 100868,
			"suite": "noble-updates",
			"version": "2.42-4ubuntu2.10"
		},
		"/noble-updates/libctf0:amd64=2.42-4ubuntu2.10": {
			"architecture": "amd64",
			"depends_on": [
				"/noble-updates/zlib1g:amd64=1:1.3.dfsg-3.1ubuntu2.1",
				"/noble-updates/libc6:amd64=2.39-0ubuntu8.7",
				"/noble-updates/libgcc-s1:amd64=14.2.0-4ubuntu2~24.04.1",
				"/noble-updates/gcc-14-base:amd64=14.2.0-4ubuntu2~24.04.1",
				"/noble-updates/libbinutils:amd64=2.42-4ubuntu2.10",
				"/noble-updates/binutils-common:amd64=2.42-4ubuntu2.10",
				"/noble-updates/libzstd1:amd64=1.5.5+dfsg2-2build1.1",
				"/noble-updates/libsframe1:amd64=2.42-4ubuntu2.10"
			],
			"filename": "pool/main/b/binutils/libctf0_2.42-4ubuntu2.10_amd64.deb",
			"name": "libctf0",
			"section": "devel",
			"sha256": "7ec86d697c3668503c85f308a6832f092075b5880ad002f22185264da0bd4645",
			"size": 94474,
			"suite": "noble-updates",
			"version": "2.42-4ubuntu2.10"
		},
		"/noble-updates/libctf0:arm64=2.42-4ubuntu2.10": {
			"architecture": "arm64",
			"depends_on": [
				"/noble-updates/zlib1g:arm64=1:1.3.dfsg-3.1ubuntu2.1",
				"/noble-updates/libc6:arm64=2.39-0ubuntu8.7",
				"/noble-updates/libgcc-s1:arm64=14.2.0-4ubuntu2~24.04.1",
				"/noble-updates/gcc-14-base:arm64=14.2.0-4ubuntu2~24.04.1",
				"/noble-updates/libbinutils:arm64=2.42-4ubuntu2.10",
				"/noble-updates/binutils-common:arm64=2.42-4ubuntu2.10",
				"/noble-updates/libzstd1:arm64=1.5.5+dfsg2-2build1.1",
				"/noble-updates/libsframe1:arm64=2.42-4ubuntu2.10"
			],
			"filename": "pool/main/b/binutils/libctf0_2.42-4ubuntu2.10_arm64.deb",
			"name": "libctf0",
			"section": "devel",
			"sha256": "2516f90d292d01eefe9207a623251550d93665f25d262f206f5c6b803389ed6b",
			"size": 95744,
			"suite": "noble-updates",
			"version": "2.42-4ubuntu2.10"
		},
		"/noble-updates/libgcc-13-dev:amd64=13.3.0-6ubuntu2~24.04.1": {
			"architecture": "amd64",
			"depends_on": [
				"/noble-updates/libquadmath0:amd64=14.2.0-4ubuntu2~24.04.1",
				"/noble-updates/libc6:amd64=2.39-0ubuntu8.7",
				"/noble-updates/libgcc-s1:amd64=14.2.0-4ubuntu2~24.04.1",
				"/noble-updates/gcc-14-base:amd64=14.2.0-4ubuntu2~24.04.1",
				"/noble-updates/libhwasan0:amd64=14.2.0-4ubuntu2~24.04.1",
				"/noble-updates/libubsan1:amd64=14.2.0-4ubuntu2~24.04.1",
				"/noble-updates/libstdc++6:amd64=14.2.0-4ubuntu2~24.04.1",
				"/noble-updates/libtsan2:amd64=14.2.0-4ubuntu2~24.04.1",
				"/noble-updates/liblsan0:amd64=14.2.0-4ubuntu2~24.04.1",
				"/noble-updates/libasan8:amd64=14.2.0-4ubuntu2~24.04.1",
				"/noble-updates/libatomic1:amd64=14.2.0-4ubuntu2~24.04.1",
				"/noble-updates/libitm1:amd64=14.2.0-4ubuntu2~24.04.1",
				"/noble-updates/libgomp1:amd64=14.2.0-4ubuntu2~24.04.1",
				"/noble-updates/gcc-13-base:amd64=13.3.0-6ubuntu2~24.04.1"
			],
			"filename": "pool/main/g/gcc-13/libgcc-13-dev_13.3.0-6ubuntu2~24.04.1_amd64.deb",
			"name": "libgcc-13-dev",
			"section": "libdevel",
			"sha256": "cd689db2691edaa10f37329307292796bb599e722e0505c79e14caaa1fe9a93a",
			"size": 2680642,
			"suite": "noble-updates",
			"version": "13.3.0-6ubuntu2~24.04.1"
		},
		"/noble-updates/libgcc-13-dev:arm64=13.3.0-6ubuntu2~24.04.1": {
			"architecture": "arm64",
			"depends_on": [
				"/noble-updates/libhwasan0:arm64=14.2.0-4ubuntu2~24.04.1",
				"/noble-updates/libgcc-s1:arm64=14.2.0-4ubuntu2~24.04.1",
				"/noble-updates/libc6:arm64=2.39-0ubuntu8.7",
				"/noble-updates/gcc-14-base:arm64=14.2.0-4ubuntu2~24.04.1",
				"/noble-updates/libubsan1:arm64=14.2.0-4ubuntu2~24.04.1",
				"/noble-updates/libstdc++6:arm64=14.2.0-4ubuntu2~24.04.1",
				"/noble-updates/libtsan2:arm64=14.2.0-4ubuntu2~24.04.1",
				"/noble-updates/liblsan0:arm64=14.2.0-4ubuntu2~24.04.1",
				"/noble-updates/libasan8:arm64=14.2.0-4ubuntu2~24.04.1",
				"/noble-updates/libatomic1:arm64=14.2.0-4ubuntu2~24.04.1",
				"/noble-updates/libitm1:arm64=14.2.0-4ubuntu2~24.04.1",
				"/noble-updates/libgomp1:arm64=14.2.0-4ubuntu2~24.04.1",
				"/noble-updates/gcc-13-base:arm64=13.3.0-6ubuntu2~24.04.1"
			],
			"filename": "pool/main/g/gcc-13/libgcc-13-dev_13.3.0-6ubuntu2~24.04.1_arm64.deb",
			"name": "libgcc-13-dev",
			"section": "libdevel",
			"sha256": "609a9410d9a1f25a1cb7847de92ee9f438336a0a3a82d282c3686f52ddd61526",
			"size": 2473368,
			"suite": "noble-updates",
			"version": "13.3.0-6ubuntu2~24.04.1"
		},
		"/noble-updates/libgcc-s1:amd64=14.2.0-4ubuntu2~24.04.1": {
			"architecture": "amd64",
			"depends_on": [
				"/noble-updates/libc6:amd64=2.39-0ubuntu8.7",
				"/noble-updates/gcc-14-base:amd64=14.2.0-4ubuntu2~24.04.1"
			],
			"filename": "pool/main/g/gcc-14/libgcc-s1_14.2.0-4ubuntu2~24.04.1_amd64.deb",
			"name": "libgcc-s1",
			"section": "libs",
			"sha256": "aa7fadbe33b78bcf99885318040601c550c208929565b179891d9a3cc2aa68cd",
			"size": 78392,
			"suite": "noble-updates",
			"version": "14.2.0-4ubuntu2~24.04.1"
		},
		"/noble-updates/libgcc-s1:arm64=14.2.0-4ubuntu2~24.04.1": {
			"architecture": "arm64",
			"depends_on": [
				"/noble-updates/libc6:arm64=2.39-0ubuntu8.7",
				"/noble-updates/gcc-14-base:arm64=14.2.0-4ubuntu2~24.04.1"
			],
			"filename": "pool/main/g/gcc-14/libgcc-s1_14.2.0-4ubuntu2~24.04.1_arm64.deb",
			"name": "libgcc-s1",
			"section": "libs",
			"sha256": "5b191f79ad985a9a653dbba45214619f729f9178a9bdf92f7c68db06c50d070b",
			"size": 61884,
			"suite": "noble-updates",
			"version": "14.2.0-4ubuntu2~24.04.1"
		},
		"/noble-updates/libgmp10:amd64=2:6.3.0+dfsg-2ubuntu6.1": {
			"architecture": "amd64",
			"depends_on": [
				"/noble-updates/libc6:amd64=2.39-0ubuntu8.7",
				"/noble-updates/libgcc-s1:amd64=14.2.0-4ubuntu2~24.04.1",
				"/noble-updates/gcc-14-base:amd64=14.2.0-4ubuntu2~24.04.1"
			],
			"filename": "pool/main/g/gmp/libgmp10_6.3.0+dfsg-2ubuntu6.1_amd64.deb",
			"name": "libgmp10",
			"section": "libs",
			"sha256": "285f8a505dfa8e1b33f357a9d8d3477ad35bf18c0b34771a6df4c25923f3ae0d",
			"size": 253460,
			"suite": "noble-updates",
			"version": "2:6.3.0+dfsg-2ubuntu6.1"
		},
		"/noble-updates/libgmp10:arm64=2:6.3.0+dfsg-2ubuntu6.1": {
			"architecture": "arm64",
			"depends_on": [
				"/noble-updates/libc6:arm64=2.39-0ubuntu8.7",
				"/noble-updates/libgcc-s1:arm64=14.2.0-4ubuntu2~24.04.1",
				"/noble-updates/gcc-14-base:arm64=14.2.0-4ubuntu2~24.04.1"
			],
			"filename": "pool/main/g/gmp/libgmp10_6.3.0+dfsg-2ubuntu6.1_arm64.deb",
			"name": "libgmp10",
			"section": "libs",
			"sha256": "5a783429ec1a29fb74a9a59c1699579dd9742bd35722280b9ce10e1f3916b003",
			"size": 243166,
			"suite": "noble-updates",
			"version": "2:6.3.0+dfsg-2ubuntu6.1"
		},
		"/noble-updates/libgomp1:amd64=14.2.0-4ubuntu2~24.04.1": {
			"architecture": "amd64",
			"depends_on": [
				"/noble-updates/libc6:amd64=2.39-0ubuntu8.7",
				"/noble-updates/libgcc-s1:amd64=14.2.0-4ubuntu2~24.04.1",
				"/noble-updates/gcc-14-base:amd64=14.2.0-4ubuntu2~24.04.1"
			],
			"filename": "pool/main/g/gcc-14/libgomp1_14.2.0-4ubuntu2~24.04.1_amd64.deb",
			"name": "libgomp1",
			"section": "libs",
			"sha256": "e8a95ec58125b4933597f30ff56c2ae10edf90f287262e366d4b6edea3019144",
			"size": 148062,
			"suite": "noble-updates",
			"version": "14.2.0-4ubuntu2~24.04.1"
		},
		"/noble-updates/libgomp1:arm64=14.2.0-4ubuntu2~24.04.1": {
			"architecture": "arm64",
			"depends_on": [
				"/noble-updates/libc6:arm64=2.39-0ubuntu8.7",
				"/noble-updates/libgcc-s1:arm64=14.2.0-4ubuntu2~24.04.1",
				"/noble-updates/gcc-14-base:arm64=14.2.0-4ubuntu2~24.04.1"
			],
			"filename": "pool/main/g/gcc-14/libgomp1_14.2.0-4ubuntu2~24.04.1_arm64.deb",
			"name": "libgomp1",
			"section": "libs",
			"sha256": "cd49d2e8834d41a6618f097b678980defeebc47271bc7c5aa8ea2c2f1a53b7a6",
			"size": 144962,
			"suite": "noble-updates",
			"version": "14.2.0-4ubuntu2~24.04.1"
		},
		"/noble-updates/libgprofng0:amd64=2.42-4ubuntu2.10": {
			"architecture": "amd64",
			"depends_on": [
				"/noble-updates/zlib1g:amd64=1:1.3.dfsg-3.1ubuntu2.1",
				"/noble-updates/libc6:amd64=2.39-0ubuntu8.7",
				"/noble-updates/libgcc-s1:amd64=14.2.0-4ubuntu2~24.04.1",
				"/noble-updates/gcc-14-base:amd64=14.2.0-4ubuntu2~24.04.1",
				"/noble-updates/libstdc++6:amd64=14.2.0-4ubuntu2~24.04.1",
				"/noble-updates/libbinutils:amd64=2.42-4ubuntu2.10",
				"/noble-updates/binutils-common:amd64=2.42-4ubuntu2.10",
				"/noble-updates/libzstd1:amd64=1.5.5+dfsg2-2build1.1",
				"/noble-updates/libsframe1:amd64=2.42-4ubuntu2.10"
			],
			"filename": "pool/main/b/binutils/libgprofng0_2.42-4ubuntu2.10_amd64.deb",
			"name": "libgprofng0",
			"section": "devel",
			"sha256": "1b7e3c2fc162e8358ca6e5a3fffdb4d0d632f790630323215841bb36a63c0ab8",
			"size": 848684,
			"suite": "noble-updates",
			"version": "2.42-4ubuntu2.10"
		},
		"/noble-updates/libgprofng0:arm64=2.42-4ubuntu2.10": {
			"architecture": "arm64",
			"depends_on": [
				"/noble-updates/zlib1g:arm64=1:1.3.dfsg-3.1ubuntu2.1",
				"/noble-updates/libc6:arm64=2.39-0ubuntu8.7",
				"/noble-updates/libgcc-s1:arm64=14.2.0-4ubuntu2~24.04.1",
				"/noble-updates/gcc-14-base:arm64=14.2.0-4ubuntu2~24.04.1",
				"/noble-updates/libstdc++6:arm64=14.2.0-4ubuntu2~24.04.1",
				"/noble-updates/libbinutils:arm64=2.42-4ubuntu2.10",
				"/noble-updates/binutils-common:arm64=2.42-4ubuntu2.10",
				"/noble-updates/libzstd1:arm64=1.5.5+dfsg2-2build1.1",
				"/noble-updates/libsframe1:arm64=2.42-4ubuntu2.10"
			],
			"filename": "pool/main/b/binutils/libgprofng0_2.42-4ubuntu2.10_arm64.deb",
			"name": "libgprofng0",
			"section": "devel",
			"sha256": "ee37f8539eab25c43bd622589932006c6ba90d44e2b7442325fc237f01a3ab5b",
			"size": 776452,
			"suite": "noble-updates",
			"version": "2.42-4ubuntu2.10"
		},
		"/noble-updates/libhwasan0:amd64=14.2.0-4ubuntu2~24.04.1": {
			"architecture": "amd64",
			"depends_on": [
				"/noble-updates/libgcc-s1:amd64=14.2.0-4ubuntu2~24.04.1",
				"/noble-updates/libc6:amd64=2.39-0ubuntu8.7",
				"/noble-updates/gcc-14-base:amd64=14.2.0-4ubuntu2~24.04.1"
			],
			"filename": "pool/main/g/gcc-14/libhwasan0_14.2.0-4ubuntu2~24.04.1_amd64.deb",
			"name": "libhwasan0",
			"section": "libs",
			"sha256": "2195318cfe68fe16b601913ef7b33c9a900372f57861643fdc9ae6fef84534cd",
			"size": 1640706,
			"suite": "noble-updates",
			"version": "14.2.0-4ubuntu2~24.04.1"
		},
		"/noble-updates/libhwasan0:arm64=14.2.0-4ubuntu2~24.04.1": {
			"architecture": "arm64",
			"depends_on": [
				"/noble-updates/libgcc-s1:arm64=14.2.0-4ubuntu2~24.04.1",
				"/noble-updates/libc6:arm64=2.39-0ubuntu8.7",
				"/noble-updates/gcc-14-base:arm64=14.2.0-4ubuntu2~24.04.1"
			],
			"filename": "pool/main/g/gcc-14/libhwasan0_14.2.0-4ubuntu2~24.04.1_arm64.deb",
			"name": "libhwasan0",
			"section": "libs",
			"sha256": "44851293eede488ad89fd12db1bd8bfcb2b732f68ad4c13b83d6e0ce5d7b4bfa",
			"size": 1604938,
			"suite": "noble-updates",
			"version": "14.2.0-4ubuntu2~24.04.1"
		},
		"/noble-updates/libitm1:amd64=14.2.0-4ubuntu2~24.04.1": {
			"architecture": "amd64",
			"depends_on": [
				"/noble-updates/libc6:amd64=2.39-0ubuntu8.7",
				"/noble-updates/libgcc-s1:amd64=14.2.0-4ubuntu2~24.04.1",
				"/noble-updates/gcc-14-base:amd64=14.2.0-4ubuntu2~24.04.1"
			],
			"filename": "pool/main/g/gcc-14/libitm1_14.2.0-4ubuntu2~24.04.1_amd64.deb",
			"name": "libitm1",
			"section": "libs",
			"sha256": "1fca498129dd3510294809d77ee754f72a9de281111200e9b7b9a5adf37faa9f",
			"size": 29702,
			"suite": "noble-updates",
			"version": "14.2.0-4ubuntu2~24.04.1"
		},
		"/noble-updates/libitm1:arm64=14.2.0-4ubuntu2~24.04.1": {
			"architecture": "arm64",
			"depends_on": [
				"/noble-updates/libc6:arm64=2.39-0ubuntu8.7",
				"/noble-updates/libgcc-s1:arm64=14.2.0-4ubuntu2~24.04.1",
				"/noble-updates/gcc-14-base:arm64=14.2.0-4ubuntu2~24.04.1"
			],
			"filename": "pool/main/g/gcc-14/libitm1_14.2.0-4ubuntu2~24.04.1_arm64.deb",
			"name": "libitm1",
			"section": "libs",
			"sha256": "7f7d7c5a26888e5e34eb62a193762eb6a8d5805c5d6f22248f638193d1804993",
			"size": 28154,
			"suite": "noble-updates",
			"version": "14.2.0-4ubuntu2~24.04.1"
		},
		"/noble-updates/liblsan0:amd64=14.2.0-4ubuntu2~24.04.1": {
			"architecture": "amd64",
			"depends_on": [
				"/noble-updates/libgcc-s1:amd64=14.2.0-4ubuntu2~24.04.1",
				"/noble-updates/libc6:amd64=2.39-0ubuntu8.7",
				"/noble-updates/gcc-14-base:amd64=14.2.0-4ubuntu2~24.04.1"
			],
			"filename": "pool/main/g/gcc-14/liblsan0_14.2.0-4ubuntu2~24.04.1_amd64.deb",
			"name": "liblsan0",
			"section": "libs",
			"sha256": "dc0c2a1a053e833ba4d71e1ec2ba4244fe301761ad4a91d6725f927a52d86a14",
			"size": 1321652,
			"suite": "noble-updates",
			"version": "14.2.0-4ubuntu2~24.04.1"
		},
		"/noble-updates/liblsan0:arm64=14.2.0-4ubuntu2~24.04.1": {
			"architecture": "arm64",
			"depends_on": [
				"/noble-updates/libgcc-s1:arm64=14.2.0-4ubuntu2~24.04.1",
				"/noble-updates/libc6:arm64=2.39-0ubuntu8.7",
				"/noble-updates/gcc-14-base:arm64=14.2.0-4ubuntu2~24.04.1"
			],
			"filename": "pool/main/g/gcc-14/liblsan0_14.2.0-4ubuntu2~24.04.1_arm64.deb",
			"name": "liblsan0",
			"section": "libs",
			"sha256": "21bb80325192b0cce6ccd041a8d823609c5e656bdda43368db6cdfe501593188",
			"size": 1289238,
			"suite": "noble-updates",
			"version": "14.2.0-4ubuntu2~24.04.1"
		},
		"/noble-updates/libpcre2-8-0:amd64=10.42-4ubuntu2.1": {
			"architecture": "amd64",
			"depends_on": [
				"/noble-updates/libc6:amd64=2.39-0ubuntu8.7",
				"/noble-updates/libgcc-s1:amd64=14.2.0-4ubuntu2~24.04.1",
				"/noble-updates/gcc-14-base:amd64=14.2.0-4ubuntu2~24.04.1"
			],
			"filename": "pool/main/p/pcre2/libpcre2-8-0_10.42-4ubuntu2.1_amd64.deb",
			"name": "libpcre2-8-0",
			"section": "libs",
			"sha256": "110a797a57673d3ee497a141cf988199258058c57525799c63194d81822529a0",
			"size": 226662,
			"suite": "noble-updates",
			"version": "10.42-4ubuntu2.1"
		},
		"/noble-updates/libpcre2-8-0:arm64=10.42-4ubuntu2.1": {
			"architecture": "arm64",
			"depends_on": [
				"/noble-updates/libc6:arm64=2.39-0ubuntu8.7",
				"/noble-updates/libgcc-s1:arm64=14.2.0-4ubuntu2~24.04.1",
				"/noble-updates/gcc-14-base:arm64=14.2.0-4ubuntu2~24.04.1"
			],
			"filename": "pool/main/p/pcre2/libpcre2-8-0_10.42-4ubuntu2.1_arm64.deb",
			"name": "libpcre2-8-0",
			"section": "libs",
			"sha256": "7581764969752953aa1f991ce143bea594d2c5d0c36c2cc98c3c614c172aba93",
			"size": 211856,
			"suite": "noble-updates",
			"version": "10.42-4ubuntu2.1"
		},
		"/noble-updates/libquadmath0:amd64=14.2.0-4ubuntu2~24.04.1": {
			"architecture": "amd64",
			"depends_on": [
				"/noble-updates/libc6:amd64=2.39-0ubuntu8.7",
				"/noble-updates/libgcc-s1:amd64=14.2.0-4ubuntu2~24.04.1",
				"/noble-updates/gcc-14-base:amd64=14.2.0-4ubuntu2~24.04.1"
			],
			"filename": "pool/main/g/gcc-14/libquadmath0_14.2.0-4ubuntu2~24.04.1_amd64.deb",
			"name": "libquadmath0",
			"section": "libs",
			"sha256": "dc8f0ca542e09d662f29370c8393c016440dd4bc5c996c5fcc19f632b63ce3b0",
			"size": 153316,
			"suite": "noble-updates",
			"version": "14.2.0-4ubuntu2~24.04.1"
		},
		"/noble-updates/libselinux1:amd64=3.5-2ubuntu2.1": {
			"architecture": "amd64",
			"depends_on": [
				"/noble-updates/libpcre2-8-0:amd64=10.42-4ubuntu2.1",
				"/noble-updates/libc6:amd64=2.39-0ubuntu8.7",
				"/noble-updates/libgcc-s1:amd64=14.2.0-4ubuntu2~24.04.1",
				"/noble-updates/gcc-14-base:amd64=14.2.0-4ubuntu2~24.04.1"
			],
			"filename": "pool/main/libs/libselinux/libselinux1_3.5-2ubuntu2.1_amd64.deb",
			"name": "libselinux1",
			"section": "libs",
			"sha256": "6abaa6c26f46ef17764c4a753e0e84de1cdadde5634fd2987621fdc617988d19",
			"size": 79660,
			"suite": "noble-updates",
			"version": "3.5-2ubuntu2.1"
		},
		"/noble-updates/libselinux1:arm64=3.5-2ubuntu2.1": {
			"architecture": "arm64",
			"depends_on": [
				"/noble-updates/libpcre2-8-0:arm64=10.42-4ubuntu2.1",
				"/noble-updates/libc6:arm64=2.39-0ubuntu8.7",
				"/noble-updates/libgcc-s1:arm64=14.2.0-4ubuntu2~24.04.1",
				"/noble-updates/gcc-14-base:arm64=14.2.0-4ubuntu2~24.04.1"
			],
			"filename": "pool/main/libs/libselinux/libselinux1_3.5-2ubuntu2.1_arm64.deb",
			"name": "libselinux1",
			"section": "libs",
			"sha256": "56630c4f009754e76808bf755072e634f8785a4dfbc8b1445213149e682f1502",
			"size": 79946,
			"suite": "noble-updates",
			"version": "3.5-2ubuntu2.1"
		},
		"/noble-updates/libsframe1:amd64=2.42-4ubuntu2.10": {
			"architecture": "amd64",
			"depends_on": [
				"/noble-updates/libc6:amd64=2.39-0ubuntu8.7",
				"/noble-updates/libgcc-s1:amd64=14.2.0-4ubuntu2~24.04.1",
				"/noble-updates/gcc-14-base:amd64=14.2.0-4ubuntu2~24.04.1"
			],
			"filename": "pool/main/b/binutils/libsframe1_2.42-4ubuntu2.10_amd64.deb",
			"name": "libsframe1",
			"section": "devel",
			"sha256": "72093fb456864db55f1352bfa5e952a94f7abaff64e71dff1fbf001db1984564",
			"size": 15724,
			"suite": "noble-updates",
			"version": "2.42-4ubuntu2.10"
		},
		"/noble-updates/libsframe1:arm64=2.42-4ubuntu2.10": {
			"architecture": "arm64",
			"depends_on": [
				"/noble-updates/libc6:arm64=2.39-0ubuntu8.7",
				"/noble-updates/libgcc-s1:arm64=14.2.0-4ubuntu2~24.04.1",
				"/noble-updates/gcc-14-base:arm64=14.2.0-4ubuntu2~24.04.1"
			],
			"filename": "pool/main/b/binutils/libsframe1_2.42-4ubuntu2.10_arm64.deb",
			"name": "libsframe1",
			"section": "devel",
			"sha256": "4e2ef8c92da324c7f8e8f055c8c698e37c93b886602766e7e72ac178835c9a31",
			"size": 15428,
			"suite": "noble-updates",
			"version": "2.42-4ubuntu2.10"
		},
		"/noble-updates/libssl3t64:amd64=3.0.13-0ubuntu3.7": {
			"architecture": "amd64",
			"depends_on": [
				"/noble-updates/libc6:amd64=2.39-0ubuntu8.7",
				"/noble-updates/libgcc-s1:amd64=14.2.0-4ubuntu2~24.04.1",
				"/noble-updates/gcc-14-base:amd64=14.2.0-4ubuntu2~24.04.1"
			],
			"filename": "pool/main/o/openssl/libssl3t64_3.0.13-0ubuntu3.7_amd64.deb",
			"name": "libssl3t64",
			"section": "libs",
			"sha256": "f9d19e6c1500cc58d90a001ef299ffa3b711e17dc5e95bf9962fb5fe1899264a",
			"size": 1941650,
			"suite": "noble-updates",
			"version": "3.0.13-0ubuntu3.7"
		},
		"/noble-updates/libssl3t64:arm64=3.0.13-0ubuntu3.7": {
			"architecture": "arm64",
			"depends_on": [
				"/noble-updates/libc6:arm64=2.39-0ubuntu8.7",
				"/noble-updates/libgcc-s1:arm64=14.2.0-4ubuntu2~24.04.1",
				"/noble-updates/gcc-14-base:arm64=14.2.0-4ubuntu2~24.04.1"
			],
			"filename": "pool/main/o/openssl/libssl3t64_3.0.13-0ubuntu3.7_arm64.deb",
			"name": "libssl3t64",
			"section": "libs",
			"sha256": "b9fbea00061d75dd4aa5342e9ed3c86eb544c99ccb4ed971f770ef6156fa0f19",
			"size": 1798052,
			"suite": "noble-updates",
			"version": "3.0.13-0ubuntu3.7"
		},
		"/noble-updates/libstdc++-13-dev:amd64=13.3.0-6ubuntu2~24.04.1": {
			"architecture": "amd64",
			"depends_on": [
				"/noble-updates/libc6-dev:amd64=2.39-0ubuntu8.7",
				"/noble/rpcsvc-proto:amd64=1.4.2-0ubuntu7",
				"/noble-updates/libc6:amd64=2.39-0ubuntu8.7",
				"/noble-updates/libgcc-s1:amd64=14.2.0-4ubuntu2~24.04.1",
				"/noble-updates/gcc-14-base:amd64=14.2.0-4ubuntu2~24.04.1",
				"/noble/libcrypt-dev:amd64=1:4.4.36-4build1",
				"/noble/libcrypt1:amd64=1:4.4.36-4build1",
				"/noble-updates/linux-libc-dev:amd64=6.8.0-106.106",
				"/noble-updates/libc-dev-bin:amd64=2.39-0ubuntu8.7",
				"/noble-updates/libstdc++6:amd64=14.2.0-4ubuntu2~24.04.1",
				"/noble-updates/libgcc-13-dev:amd64=13.3.0-6ubuntu2~24.04.1",
				"/noble-updates/libquadmath0:amd64=14.2.0-4ubuntu2~24.04.1",
				"/noble-updates/libhwasan0:amd64=14.2.0-4ubuntu2~24.04.1",
				"/noble-updates/libubsan1:amd64=14.2.0-4ubuntu2~24.04.1",
				"/noble-updates/libtsan2:amd64=14.2.0-4ubuntu2~24.04.1",
				"/noble-updates/liblsan0:amd64=14.2.0-4ubuntu2~24.04.1",
				"/noble-updates/libasan8:amd64=14.2.0-4ubuntu2~24.04.1",
				"/noble-updates/libatomic1:amd64=14.2.0-4ubuntu2~24.04.1",
				"/noble-updates/libitm1:amd64=14.2.0-4ubuntu2~24.04.1",
				"/noble-updates/libgomp1:amd64=14.2.0-4ubuntu2~24.04.1",
				"/noble-updates/gcc-13-base:amd64=13.3.0-6ubuntu2~24.04.1"
			],
			"filename": "pool/main/g/gcc-13/libstdc++-13-dev_13.3.0-6ubuntu2~24.04.1_amd64.deb",
			"name": "libstdc++-13-dev",
			"section": "libdevel",
			"sha256": "ee5633e863e19c3381ed97842ce35ed32ede96a3d1ae4e94c051d3036fe21347",
			"size": 2419834,
			"suite": "noble-updates",
			"version": "13.3.0-6ubuntu2~24.04.1"
		},
		"/noble-updates/libstdc++-13-dev:arm64=13.3.0-6ubuntu2~24.04.1": {
			"architecture": "arm64",
			"depends_on": [
				"/noble-updates/libc6-dev:arm64=2.39-0ubuntu8.7",
				"/noble/rpcsvc-proto:arm64=1.4.2-0ubuntu7",
				"/noble-updates/libc6:arm64=2.39-0ubuntu8.7",
				"/noble-updates/libgcc-s1:arm64=14.2.0-4ubuntu2~24.04.1",
				"/noble-updates/gcc-14-base:arm64=14.2.0-4ubuntu2~24.04.1",
				"/noble/libcrypt-dev:arm64=1:4.4.36-4build1",
				"/noble/libcrypt1:arm64=1:4.4.36-4build1",
				"/noble-updates/linux-libc-dev:arm64=6.8.0-106.106",
				"/noble-updates/libc-dev-bin:arm64=2.39-0ubuntu8.7",
				"/noble-updates/libstdc++6:arm64=14.2.0-4ubuntu2~24.04.1",
				"/noble-updates/libgcc-13-dev:arm64=13.3.0-6ubuntu2~24.04.1",
				"/noble-updates/libhwasan0:arm64=14.2.0-4ubuntu2~24.04.1",
				"/noble-updates/libubsan1:arm64=14.2.0-4ubuntu2~24.04.1",
				"/noble-updates/libtsan2:arm64=14.2.0-4ubuntu2~24.04.1",
				"/noble-updates/liblsan0:arm64=14.2.0-4ubuntu2~24.04.1",
				"/noble-updates/libasan8:arm64=14.2.0-4ubuntu2~24.04.1",
				"/noble-updates/libatomic1:arm64=14.2.0-4ubuntu2~24.04.1",
				"/noble-updates/libitm1:arm64=14.2.0-4ubuntu2~24.04.1",
				"/noble-updates/libgomp1:arm64=14.2.0-4ubuntu2~24.04.1",
				"/noble-updates/gcc-13-base:arm64=13.3.0-6ubuntu2~24.04.1"
			],
			"filename": "pool/main/g/gcc-13/libstdc++-13-dev_13.3.0-6ubuntu2~24.04.1_arm64.deb",
			"name": "libstdc++-13-dev",
			"section": "libdevel",
			"sha256": "e4911c9281d73b318ca47cb7976011a7dc13e299a91a06bc6d3e2d174cc2ce51",
			"size": 2397276,
			"suite": "noble-updates",
			"version": "13.3.0-6ubuntu2~24.04.1"
		},
		"/noble-updates/libstdc++6:amd64=14.2.0-4ubuntu2~24.04.1": {
			"architecture": "amd64",
			"depends_on": [
				"/noble-updates/libgcc-s1:amd64=14.2.0-4ubuntu2~24.04.1",
				"/noble-updates/libc6:amd64=2.39-0ubuntu8.7",
				"/noble-updates/gcc-14-base:amd64=14.2.0-4ubuntu2~24.04.1"
			],
			"filename": "pool/main/g/gcc-14/libstdc++6_14.2.0-4ubuntu2~24.04.1_amd64.deb",
			"name": "libstdc++6",
			"section": "libs",
			"sha256": "a51f8de7829211db961a31f02158058ad1a95f92ac6d0a5dff6350e2821c54c0",
			"size": 792064,
			"suite": "noble-updates",
			"version": "14.2.0-4ubuntu2~24.04.1"
		},
		"/noble-updates/libstdc++6:arm64=14.2.0-4ubuntu2~24.04.1": {
			"architecture": "arm64",
			"depends_on": [
				"/noble-updates/libgcc-s1:arm64=14.2.0-4ubuntu2~24.04.1",
				"/noble-updates/libc6:arm64=2.39-0ubuntu8.7",
				"/noble-updates/gcc-14-base:arm64=14.2.0-4ubuntu2~24.04.1"
			],
			"filename": "pool/main/g/gcc-14/libstdc++6_14.2.0-4ubuntu2~24.04.1_arm64.deb",
			"name": "libstdc++6",
			"section": "libs",
			"sha256": "f84a05ac45a6884109b6527e911081a38263b89e042fc94a338cf975f61a330c",
			"size": 750976,
			"suite": "noble-updates",
			"version": "14.2.0-4ubuntu2~24.04.1"
		},
		"/noble-updates/libtsan2:amd64=14.2.0-4ubuntu2~24.04.1": {
			"architecture": "amd64",
			"depends_on": [
				"/noble-updates/libgcc-s1:amd64=14.2.0-4ubuntu2~24.04.1",
				"/noble-updates/libc6:amd64=2.39-0ubuntu8.7",
				"/noble-updates/gcc-14-base:amd64=14.2.0-4ubuntu2~24.04.1"
			],
			"filename": "pool/main/g/gcc-14/libtsan2_14.2.0-4ubuntu2~24.04.1_amd64.deb",
			"name": "libtsan2",
			"section": "libs",
			"sha256": "8cbcc9b3ae5ef23b449383d47a9035b27596e307d7dce7df9b83d47a7acd1d91",
			"size": 2771910,
			"suite": "noble-updates",
			"version": "14.2.0-4ubuntu2~24.04.1"
		},
		"/noble-updates/libtsan2:arm64=14.2.0-4ubuntu2~24.04.1": {
			"architecture": "arm64",
			"depends_on": [
				"/noble-updates/libgcc-s1:arm64=14.2.0-4ubuntu2~24.04.1",
				"/noble-updates/libc6:arm64=2.39-0ubuntu8.7",
				"/noble-updates/gcc-14-base:arm64=14.2.0-4ubuntu2~24.04.1"
			],
			"filename": "pool/main/g/gcc-14/libtsan2_14.2.0-4ubuntu2~24.04.1_arm64.deb",
			"name": "libtsan2",
			"section": "libs",
			"sha256": "00beb501f4979c7fd3a978b52a489ea7dbfc1203e5c56936e4c0ea5c2032fb3d",
			"size": 2696830,
			"suite": "noble-updates",
			"version": "14.2.0-4ubuntu2~24.04.1"
		},
		"/noble-updates/libubsan1:amd64=14.2.0-4ubuntu2~24.04.1": {
			"architecture": "amd64",
			"depends_on": [
				"/noble-updates/libstdc++6:amd64=14.2.0-4ubuntu2~24.04.1",
				"/noble-updates/libgcc-s1:amd64=14.2.0-4ubuntu2~24.04.1",
				"/noble-updates/libc6:amd64=2.39-0ubuntu8.7",
				"/noble-updates/gcc-14-base:amd64=14.2.0-4ubuntu2~24.04.1"
			],
			"filename": "pool/main/g/gcc-14/libubsan1_14.2.0-4ubuntu2~24.04.1_amd64.deb",
			"name": "libubsan1",
			"section": "libs",
			"sha256": "a16dea3abe2dcac99bcfae27e7e5672fde64573c3c170dcb0cd55631238f9814",
			"size": 1183812,
			"suite": "noble-updates",
			"version": "14.2.0-4ubuntu2~24.04.1"
		},
		"/noble-updates/libubsan1:arm64=14.2.0-4ubuntu2~24.04.1": {
			"architecture": "arm64",
			"depends_on": [
				"/noble-updates/libstdc++6:arm64=14.2.0-4ubuntu2~24.04.1",
				"/noble-updates/libgcc-s1:arm64=14.2.0-4ubuntu2~24.04.1",
				"/noble-updates/libc6:arm64=2.39-0ubuntu8.7",
				"/noble-updates/gcc-14-base:arm64=14.2.0-4ubuntu2~24.04.1"
			],
			"filename": "pool/main/g/gcc-14/libubsan1_14.2.0-4ubuntu2~24.04.1_arm64.deb",
			"name": "libubsan1",
			"section": "libs",
			"sha256": "a5b4383f70f41cd949315c89e99e6416a0ee48037f7c5ea6b33f88f3c733757a",
			"size": 1157016,
			"suite": "noble-updates",
			"version": "14.2.0-4ubuntu2~24.04.1"
		},
		"/noble-updates/libzstd1:amd64=1.5.5+dfsg2-2build1.1": {
			"architecture": "amd64",
			"depends_on": [
				"/noble-updates/libc6:amd64=2.39-0ubuntu8.7",
				"/noble-updates/libgcc-s1:amd64=14.2.0-4ubuntu2~24.04.1",
				"/noble-updates/gcc-14-base:amd64=14.2.0-4ubuntu2~24.04.1"
			],
			"filename": "pool/main/libz/libzstd/libzstd1_1.5.5+dfsg2-2build1.1_amd64.deb",
			"name": "libzstd1",
			"section": "libs",
			"sha256": "dfcf25061e07aad7efd3f4f880ba5ad4d4d09ebe7fc8cc77ab6b8a161d6d4727",
			"size": 299472,
			"suite": "noble-updates",
			"version": "1.5.5+dfsg2-2build1.1"
		},
		"/noble-updates/libzstd1:arm64=1.5.5+dfsg2-2build1.1": {
			"architecture": "arm64",
			"depends_on": [
				"/noble-updates/libc6:arm64=2.39-0ubuntu8.7",
				"/noble-updates/libgcc-s1:arm64=14.2.0-4ubuntu2~24.04.1",
				"/noble-updates/gcc-14-base:arm64=14.2.0-4ubuntu2~24.04.1"
			],
			"filename": "pool/main/libz/libzstd/libzstd1_1.5.5+dfsg2-2build1.1_arm64.deb",
			"name": "libzstd1",
			"section": "libs",
			"sha256": "ea7d6e9fde577ea14dbf07fdfb74d6287eb09c6cba4a9d63abdcb87b0ec54bcc",
			"size": 271278,
			"suite": "noble-updates",
			"version": "1.5.5+dfsg2-2build1.1"
		},
		"/noble-updates/linux-libc-dev:amd64=6.8.0-106.106": {
			"architecture": "amd64",
			"depends_on": [],
			"filename": "pool/main/l/linux/linux-libc-dev_6.8.0-106.106_amd64.deb",
			"name": "linux-libc-dev",
			"section": "devel",
			"sha256": "dbef5eaae5d6497ccf30c6a082bbba5a294ab3f8e210ae6ff936caf942b8ed2d",
			"size": 2094960,
			"suite": "noble-updates",
			"version": "6.8.0-106.106"
		},
		"/noble-updates/linux-libc-dev:arm64=6.8.0-106.106": {
			"architecture": "arm64",
			"depends_on": [],
			"filename": "pool/main/l/linux/linux-libc-dev_6.8.0-106.106_arm64.deb",
			"name": "linux-libc-dev",
			"section": "devel",
			"sha256": "55b43c3791fec36a0a217fb2fa1572d599370d38674cfeae8cbc9d102b87ebfd",
			"size": 2068572,
			"suite": "noble-updates",
			"version": "6.8.0-106.106"
		},
		"/noble-updates/zlib1g:amd64=1:1.3.dfsg-3.1ubuntu2.1": {
			"architecture": "amd64",
			"depends_on": [
				"/noble-updates/libc6:amd64=2.39-0ubuntu8.7",
				"/noble-updates/libgcc-s1:amd64=14.2.0-4ubuntu2~24.04.1",
				"/noble-updates/gcc-14-base:amd64=14.2.0-4ubuntu2~24.04.1"
			],
			"filename": "pool/main/z/zlib/zlib1g_1.3.dfsg-3.1ubuntu2.1_amd64.deb",
			"name": "zlib1g",
			"section": "libs",
			"sha256": "7074b6a2f6367a10d280c00a1cb02e74277709180bab4f2491a2f355ab2d6c20",
			"size": 62850,
			"suite": "noble-updates",
			"version": "1:1.3.dfsg-3.1ubuntu2.1"
		},
		"/noble-updates/zlib1g:arm64=1:1.3.dfsg-3.1ubuntu2.1": {
			"architecture": "arm64",
			"depends_on": [
				"/noble-updates/libc6:arm64=2.39-0ubuntu8.7",
				"/noble-updates/libgcc-s1:arm64=14.2.0-4ubuntu2~24.04.1",
				"/noble-updates/gcc-14-base:arm64=14.2.0-4ubuntu2~24.04.1"
			],
			"filename": "pool/main/z/zlib/zlib1g_1.3.dfsg-3.1ubuntu2.1_arm64.deb",
			"name": "zlib1g",
			"section": "libs",
			"sha256": "cbe3d39ec32d3cc27c021ae4af11e7c67bdf9d700d573207e0941d4038056278",
			"size": 61736,
			"suite": "noble-updates",
			"version": "1:1.3.dfsg-3.1ubuntu2.1"
		},
		"/noble/bash:amd64=5.2.21-2ubuntu4": {
			"architecture": "amd64",
			"depends_on": [
				"/noble/debianutils:amd64=5.17build1",
				"/noble-updates/libc6:amd64=2.39-0ubuntu8.7",
				"/noble-updates/libgcc-s1:amd64=14.2.0-4ubuntu2~24.04.1",
				"/noble-updates/gcc-14-base:amd64=14.2.0-4ubuntu2~24.04.1",
				"/noble-updates/base-files:amd64=13ubuntu10.4",
				"/noble/libcrypt1:amd64=1:4.4.36-4build1",
				"/noble/mawk:amd64=1.3.4.20240123-1build1",
				"/noble/libtinfo6:amd64=6.4+20240113-1ubuntu2"
			],
			"filename": "pool/main/b/bash/bash_5.2.21-2ubuntu4_amd64.deb",
			"name": "bash",
			"section": "shells",
			"sha256": "73de311a21e094e29ac01527d2b52226cc87fde0a5b57032902251b426d92c66",
			"size": 794086,
			"suite": "noble",
			"version": "5.2.21-2ubuntu4"
		},
		"/noble/bash:arm64=5.2.21-2ubuntu4": {
			"architecture": "arm64",
			"depends_on": [
				"/noble/debianutils:arm64=5.17build1",
				"/noble-updates/libc6:arm64=2.39-0ubuntu8.7",
				"/noble-updates/libgcc-s1:arm64=14.2.0-4ubuntu2~24.04.1",
				"/noble-updates/gcc-14-base:arm64=14.2.0-4ubuntu2~24.04.1",
				"/noble-updates/base-files:arm64=13ubuntu10.4",
				"/noble/libcrypt1:arm64=1:4.4.36-4build1",
				"/noble/mawk:arm64=1.3.4.20240123-1build1",
				"/noble/libtinfo6:arm64=6.4+20240113-1ubuntu2"
			],
			"filename": "pool/main/b/bash/bash_5.2.21-2ubuntu4_arm64.deb",
			"name": "bash",
			"section": "shells",
			"sha256": "1cb8aa182b8124a5304b5d5cf24300e295c9f6ff22a2565fcecae686c0492f09",
			"size": 780262,
			"suite": "noble",
			"version": "5.2.21-2ubuntu4"
		},
		"/noble/debianutils:amd64=5.17build1": {
			"architecture": "amd64",
			"depends_on": [
				"/noble-updates/libc6:amd64=2.39-0ubuntu8.7",
				"/noble-updates/libgcc-s1:amd64=14.2.0-4ubuntu2~24.04.1",
				"/noble-updates/gcc-14-base:amd64=14.2.0-4ubuntu2~24.04.1"
			],
			"filename": "pool/main/d/debianutils/debianutils_5.17build1_amd64.deb",
			"name": "debianutils",
			"section": "utils",
			"sha256": "1047a9a57018e18531f76e5b00e226a68554b6f1d147f2a5c1b32518c7b20636",
			"size": 89890,
			"suite": "noble",
			"version": "5.17build1"
		},
		"/noble/debianutils:arm64=5.17build1": {
			"architecture": "arm64",
			"depends_on": [
				"/noble-updates/libc6:arm64=2.39-0ubuntu8.7",
				"/noble-updates/libgcc-s1:arm64=14.2.0-4ubuntu2~24.04.1",
				"/noble-updates/gcc-14-base:arm64=14.2.0-4ubuntu2~24.04.1"
			],
			"filename": "pool/main/d/debianutils/debianutils_5.17build1_arm64.deb",
			"name": "debianutils",
			"section": "utils",
			"sha256": "7419da04f9c467986b2176e799f3683b9403c643966084d0f6054f2a5b8919e9",
			"size": 90236,
			"suite": "noble",
			"version": "5.17build1"
		},
		"/noble/libcrypt-dev:amd64=1:4.4.36-4build1": {
			"architecture": "amd64",
			"depends_on": [
				"/noble/libcrypt1:amd64=1:4.4.36-4build1",
				"/noble-updates/libc6:amd64=2.39-0ubuntu8.7",
				"/noble-updates/libgcc-s1:amd64=14.2.0-4ubuntu2~24.04.1",
				"/noble-updates/gcc-14-base:amd64=14.2.0-4ubuntu2~24.04.1"
			],
			"filename": "pool/main/libx/libxcrypt/libcrypt-dev_4.4.36-4build1_amd64.deb",
			"name": "libcrypt-dev",
			"section": "libdevel",
			"sha256": "2edff420ef80b4a3f3751e65c33423ef30e563122a58b759e4854ea8d84ba1b1",
			"size": 111780,
			"suite": "noble",
			"version": "1:4.4.36-4build1"
		},
		"/noble/libcrypt-dev:arm64=1:4.4.36-4build1": {
			"architecture": "arm64",
			"depends_on": [
				"/noble/libcrypt1:arm64=1:4.4.36-4build1",
				"/noble-updates/libc6:arm64=2.39-0ubuntu8.7",
				"/noble-updates/libgcc-s1:arm64=14.2.0-4ubuntu2~24.04.1",
				"/noble-updates/gcc-14-base:arm64=14.2.0-4ubuntu2~24.04.1"
			],
			"filename": "pool/main/libx/libxcrypt/libcrypt-dev_4.4.36-4build1_arm64.deb",
			"name": "libcrypt-dev",
			"section": "libdevel",
			"sha256": "cadcc00021aa1082a8cb5cd1c2686b25b7a4d396f2029eaa1b12159ca46f1766",
			"size": 118238,
			"suite": "noble",
			"version": "1:4.4.36-4build1"
		},
		"/noble/libcrypt1:amd64=1:4.4.36-4build1": {
			"architecture": "amd64",
			"depends_on": [
				"/noble-updates/libc6:amd64=2.39-0ubuntu8.7",
				"/noble-updates/libgcc-s1:amd64=14.2.0-4ubuntu2~24.04.1",
				"/noble-updates/gcc-14-base:amd64=14.2.0-4ubuntu2~24.04.1"
			],
			"filename": "pool/main/libx/libxcrypt/libcrypt1_4.4.36-4build1_amd64.deb",
			"name": "libcrypt1",
			"section": "libs",
			"sha256": "9474785cd6f398512bf8c305c3901dbb111569dccb6f5832002373c0a8ac5832",
			"size": 82302,
			"suite": "noble",
			"version": "1:4.4.36-4build1"
		},
		"/noble/libcrypt1:arm64=1:4.4.36-4build1": {
			"architecture": "arm64",
			"depends_on": [
				"/noble-updates/libc6:arm64=2.39-0ubuntu8.7",
				"/noble-updates/libgcc-s1:arm64=14.2.0-4ubuntu2~24.04.1",
				"/noble-updates/gcc-14-base:arm64=14.2.0-4ubuntu2~24.04.1"
			],
			"filename": "pool/main/libx/libxcrypt/libcrypt1_4.4.36-4build1_arm64.deb",
			"name": "libcrypt1",
			"section": "libs",
			"sha256": "5cd73ba112507dabd8e43b528ca9f530719a370e014b8e3e797770e6e940cccf",
			"size": 85888,
			"suite": "noble",
			"version": "1:4.4.36-4build1"
		},
		"/noble/libjansson4:amd64=2.14-2build2": {
			"architecture": "amd64",
			"depends_on": [
				"/noble-updates/libc6:amd64=2.39-0ubuntu8.7",
				"/noble-updates/libgcc-s1:amd64=14.2.0-4ubuntu2~24.04.1",
				"/noble-updates/gcc-14-base:amd64=14.2.0-4ubuntu2~24.04.1"
			],
			"filename": "pool/main/j/jansson/libjansson4_2.14-2build2_amd64.deb",
			"name": "libjansson4",
			"section": "libs",
			"sha256": "0cf79113f5d193ce9af2be2ff4b2c3b30dd4e55a0b6c47f7d28f6c849ff3aa60",
			"size": 32830,
			"suite": "noble",
			"version": "2.14-2build2"
		},
		"/noble/libjansson4:arm64=2.14-2build2": {
			"architecture": "arm64",
			"depends_on": [
				"/noble-updates/libc6:arm64=2.39-0ubuntu8.7",
				"/noble-updates/libgcc-s1:arm64=14.2.0-4ubuntu2~24.04.1",
				"/noble-updates/gcc-14-base:arm64=14.2.0-4ubuntu2~24.04.1"
			],
			"filename": "pool/main/j/jansson/libjansson4_2.14-2build2_arm64.deb",
			"name": "libjansson4",
			"section": "libs",
			"sha256": "a9d513eae76f4efb1c7370413bd21634fcfc0955e103d26af95f298af6c90abd",
			"size": 34362,
			"suite": "noble",
			"version": "2.14-2build2"
		},
		"/noble/libtinfo6:amd64=6.4+20240113-1ubuntu2": {
			"architecture": "amd64",
			"depends_on": [
				"/noble-updates/libc6:amd64=2.39-0ubuntu8.7",
				"/noble-updates/libgcc-s1:amd64=14.2.0-4ubuntu2~24.04.1",
				"/noble-updates/gcc-14-base:amd64=14.2.0-4ubuntu2~24.04.1"
			],
			"filename": "pool/main/n/ncurses/libtinfo6_6.4+20240113-1ubuntu2_amd64.deb",
			"name": "libtinfo6",
			"section": "libs",
			"sha256": "53e1e1753729d04cf65b05e6e58abe06e2bb76cc07eff0e1b2a638a638ca209b",
			"size": 107794,
			"suite": "noble",
			"version": "6.4+20240113-1ubuntu2"
		},
		"/noble/libtinfo6:arm64=6.4+20240113-1ubuntu2": {
			"architecture": "arm64",
			"depends_on": [
				"/noble-updates/libc6:arm64=2.39-0ubuntu8.7",
				"/noble-updates/libgcc-s1:arm64=14.2.0-4ubuntu2~24.04.1",
				"/noble-updates/gcc-14-base:arm64=14.2.0-4ubuntu2~24.04.1"
			],
			"filename": "pool/main/n/ncurses/libtinfo6_6.4+20240113-1ubuntu2_arm64.deb",
			"name": "libtinfo6",
			"section": "libs",
			"sha256": "e8d06277be81d0f6e7d49ce796a477a9fc88e755bf3048e0afe44fc14a310b72",
			"size": 104360,
			"suite": "noble",
			"version": "6.4+20240113-1ubuntu2"
		},
		"/noble/mawk:amd64=1.3.4.20240123-1build1": {
			"architecture": "amd64",
			"depends_on": [
				"/noble-updates/libc6:amd64=2.39-0ubuntu8.7",
				"/noble-updates/libgcc-s1:amd64=14.2.0-4ubuntu2~24.04.1",
				"/noble-updates/gcc-14-base:amd64=14.2.0-4ubuntu2~24.04.1"
			],
			"filename": "pool/main/m/mawk/mawk_1.3.4.20240123-1build1_amd64.deb",
			"name": "mawk",
			"section": "utils",
			"sha256": "dc7f7f4dad4b48f6012ea65de3198d8376604afef39f06d65ec6167740e203c9",
			"size": 127222,
			"suite": "noble",
			"version": "1.3.4.20240123-1build1"
		},
		"/noble/mawk:arm64=1.3.4.20240123-1build1": {
			"architecture": "arm64",
			"depends_on": [
				"/noble-updates/libc6:arm64=2.39-0ubuntu8.7",
				"/noble-updates/libgcc-s1:arm64=14.2.0-4ubuntu2~24.04.1",
				"/noble-updates/gcc-14-base:arm64=14.2.0-4ubuntu2~24.04.1"
			],
			"filename": "pool/main/m/mawk/mawk_1.3.4.20240123-1build1_arm64.deb",
			"name": "mawk",
			"section": "utils",
			"sha256": "a6fa75e49de6327ccdbf664e905cde229df77116a966c310e81c778eba756dca",
			"size": 123594,
			"suite": "noble",
			"version": "1.3.4.20240123-1build1"
		},
		"/noble/rpcsvc-proto:amd64=1.4.2-0ubuntu7": {
			"architecture": "amd64",
			"depends_on": [
				"/noble-updates/libc6:amd64=2.39-0ubuntu8.7",
				"/noble-updates/libgcc-s1:amd64=14.2.0-4ubuntu2~24.04.1",
				"/noble-updates/gcc-14-base:amd64=14.2.0-4ubuntu2~24.04.1"
			],
			"filename": "pool/main/r/rpcsvc-proto/rpcsvc-proto_1.4.2-0ubuntu7_amd64.deb",
			"name": "rpcsvc-proto",
			"section": "libs",
			"sha256": "7eb710fe148d224c159ddec1ceb0ba53ead52a80a6793dcdae1474acf20d8f71",
			"size": 67446,
			"suite": "noble",
			"version": "1.4.2-0ubuntu7"
		},
		"/noble/rpcsvc-proto:arm64=1.4.2-0ubuntu7": {
			"architecture": "arm64",
			"depends_on": [
				"/noble-updates/libc6:arm64=2.39-0ubuntu8.7",
				"/noble-updates/libgcc-s1:arm64=14.2.0-4ubuntu2~24.04.1",
				"/noble-updates/gcc-14-base:arm64=14.2.0-4ubuntu2~24.04.1"
			],
			"filename": "pool/main/r/rpcsvc-proto/rpcsvc-proto_1.4.2-0ubuntu7_arm64.deb",
			"name": "rpcsvc-proto",
			"section": "libs",
			"sha256": "ae527152fc2bf9c1a645c2620d802b0849db32c8aa48328b4ae94c59cc57bcc9",
			"size": 64816,
			"suite": "noble",
			"version": "1.4.2-0ubuntu7"
		}
	},
	"sources": {
		"noble": {
			"architectures": [
				"amd64",
				"arm64"
			],
			"components": [
				"main"
			],
			"types": [
				"deb"
			],
			"uris": [
				"https://snapshot.ubuntu.com/ubuntu/20260401T000000Z"
			]
		},
		"noble-security": {
			"architectures": [
				"amd64",
				"arm64"
			],
			"components": [
				"main"
			],
			"types": [
				"deb"
			],
			"uris": [
				"https://snapshot.ubuntu.com/ubuntu/20260401T000000Z"
			]
		},
		"noble-updates": {
			"architectures": [
				"amd64",
				"arm64"
			],
			"components": [
				"main"
			],
			"types": [
				"deb"
			],
			"uris": [
				"https://snapshot.ubuntu.com/ubuntu/20260401T000000Z"
			]
		}
	},
	"version": 2
}
